otodom/__init__.py
otodom/category.py
otodom/offer.py
otodom/utils.py
pyotodom-0.0.2.dist-info/DESCRIPTION.rst
pyotodom-0.0.2.dist-info/METADATA
pyotodom-0.0.2.dist-info/RECORD
pyotodom-0.0.2.dist-info/WHEEL
pyotodom-0.0.2.dist-info/metadata.json
pyotodom-0.0.2.dist-info/top_level.txt
