Metadata-Version: 2.0
Name: pyotodom
Version: 0.0.2
Summary: pyotodom - python wrapper for otodom
Home-page: https://github.com/limebrains/pyotodom
Author: LimeBrains
Author-email: mail@limebrains.com
License: UNKNOWN
Platform: UNKNOWN
